scopro_python/__init__.py
scopro_python/scopro.py
scopro_python-0.1.0.dist-info/LICENSE
scopro_python-0.1.0.dist-info/METADATA
scopro_python-0.1.0.dist-info/WHEEL
scopro_python-0.1.0.dist-info/top_level.txt
scopro_python-0.1.0.dist-info/RECORD
